LICENSE
MANIFEST.in
README.rst
example.py
example_notify_email.py
example_yaml.py
setup.py
OpScripts.egg-info/PKG-INFO
OpScripts.egg-info/SOURCES.txt
OpScripts.egg-info/dependency_links.txt
OpScripts.egg-info/top_level.txt
OpScripts.egg-info/zip-safe
opscripts/__init__.py
opscripts/config/__init__.py
opscripts/config/v4.py
opscripts/config/v5.py
opscripts/config/v6.py
opscripts/logging/__init__.py
opscripts/logging/v1.py
opscripts/logging/v2.py
opscripts/notify/__init__.py
opscripts/notify/email/__init__.py
opscripts/notify/email/v2.py
opscripts/notify/email/v3.py
opscripts/utils/__init__.py
opscripts/utils/v4.py
opscripts/utils/v5.py
opscripts/utils/v6.py
opscripts/utils/v7.py
opscripts/utils/v8.py
opscripts/yaml/__init__.py
opscripts/yaml/v1.py