Metadata-Version: 1.1
Name: OpScripts
Version: 1.6.6
Summary: Python libraries to assist with writing Linux Ops scripts.
